setup.py
mongo_util/__init__.py
mongo_util/mongo_util.py
mongo_util.egg-info/PKG-INFO
mongo_util.egg-info/SOURCES.txt
mongo_util.egg-info/dependency_links.txt
mongo_util.egg-info/top_level.txt